inquirer_console/__init__.py
inquirer_console/prompt.py
inquirer_console/prompts/__init__.py
inquirer_console/prompts/checkbox.py
inquirer_console/prompts/confirm.py
inquirer_console/prompts/input.py
inquirer_console/prompts/password.py
inquirer_console/prompts/radio.py
inquirer_console/prompts/text.py
inquirer_console/utils/__init__.py
inquirer_console/utils/keyboard.py
inquirer_console-1.1.0.dist-info/METADATA
inquirer_console-1.1.0.dist-info/WHEEL
inquirer_console-1.1.0.dist-info/licenses/LICENSE
inquirer_console-1.1.0.dist-info/RECORD
