Metadata-Version: 2.4
Name: inquirer_console
Version: 1.1.0
Summary: Elegant interactive command-line interface tool library, Python implementation of Inquirer.js
Project-URL: Homepage, https://github.com/Eusen/inquirer_console
Project-URL: Documentation, https://github.com/Eusen/inquirer_console#readme
Project-URL: Bug Tracker, https://github.com/Eusen/inquirer_console/issues
Project-URL: Release notes, https://github.com/Eusen/inquirer_console/releases
Author-email: Eusen <179530591@qq.com>
Maintainer-email: Eusen <179530591@qq.com>
License: Apache-2.0
License-File: LICENSE
Keywords: cli,command-line,console,inquirer,interactive,prompt,tui
Classifier: Development Status :: 5 - Production/Stable
Classifier: Environment :: Console
Classifier: Intended Audience :: Developers
Classifier: License :: OSI Approved :: Apache Software License
Classifier: License :: OSI Approved :: MIT License
Classifier: Programming Language :: Python :: 3
Classifier: Programming Language :: Python :: 3.9
Classifier: Programming Language :: Python :: 3.10
Classifier: Programming Language :: Python :: 3.11
Classifier: Programming Language :: Python :: 3.12
Classifier: Programming Language :: Python :: 3.13
Classifier: Topic :: Software Development :: Libraries :: Python Modules
Classifier: Topic :: Software Development :: User Interfaces
Requires-Python: >=3
